infocards/archive.py
infocards/card.py
infocards/exceptions.py
infocards/models.py
infocards/_version.py
infocards/__init__.py
infocards-0.5.3.dist-info/DESCRIPTION.rst
infocards-0.5.3.dist-info/METADATA
infocards-0.5.3.dist-info/metadata.json
infocards-0.5.3.dist-info/pbr.json
infocards-0.5.3.dist-info/RECORD
infocards-0.5.3.dist-info/top_level.txt
infocards-0.5.3.dist-info/WHEEL
