Metadata-Version: 2.0
Name: infocards
Version: 0.5.3
Summary: Simple information card archive library
Home-page: https://github.com/rmed/infocards
Author: Rafael Medina García
Author-email: rafamedgar@gmail.com
License: GPLv2+
Keywords: information info card archive database
Platform: UNKNOWN
Classifier: Development Status :: 5 - Production/Stable
Classifier: Intended Audience :: Developers
Classifier: Topic :: Database
Classifier: Topic :: Utilities
Classifier: License :: OSI Approved :: GNU General Public License v2 or later (GPLv2+)
Classifier: Programming Language :: Python :: 2
Classifier: Programming Language :: Python :: 2.7
Classifier: Programming Language :: Python :: 3
Classifier: Programming Language :: Python :: 3.4
Requires-Dist: python-Levenshtein (==0.12.0)
Requires-Dist: fuzzywuzzy (==0.5.0)
Requires-Dist: peewee (==2.6.3)
